jetblack_serialization/__init__.py
jetblack_serialization/config.py
jetblack_serialization/custom_annotations.py
jetblack_serialization/py.typed
jetblack_serialization/types.py
jetblack_serialization/typing_ex.py
jetblack_serialization/utils.py
jetblack_serialization/json/__init__.py
jetblack_serialization/json/annotations.py
jetblack_serialization/json/encoding.py
jetblack_serialization/json/serialization.py
jetblack_serialization/json/typed_deserializer.py
jetblack_serialization/json/typed_serializer.py
jetblack_serialization/json/untyped_deserializer.py
jetblack_serialization/json/untyped_serializer.py
jetblack_serialization/xml/__init__.py
jetblack_serialization/xml/annotations.py
jetblack_serialization/xml/encoding.py
jetblack_serialization/xml/serialization.py
jetblack_serialization/xml/typed_deserializer.py
jetblack_serialization/xml/typed_serializer.py
jetblack_serialization/xml/untyped_deserializer.py
jetblack_serialization/xml/untyped_serializer.py
jetblack_serialization/yaml/__init__.py
jetblack_serialization/yaml/encoding.py
jetblack_serialization/yaml/serialization.py
jetblack_serialization/yaml/typed_deserializer.py
jetblack_serialization/yaml/typed_serializer.py
jetblack_serialization/yaml/untyped_deserializer.py
jetblack_serialization/yaml/untyped_serializer.py
jetblack_serialization-4.0.13.dist-info/licenses/LICENSE
jetblack_serialization-4.0.13.dist-info/METADATA
jetblack_serialization-4.0.13.dist-info/WHEEL
jetblack_serialization-4.0.13.dist-info/top_level.txt
jetblack_serialization-4.0.13.dist-info/RECORD
