Metadata-Version: 2.4
Name: jetblack-serialization
Version: 4.0.13
Summary: Serialization for JSON, YAML and XML using typing
Author-email: Rob Blackbourn <rob.blackbourn@gmail.com>
License: Apache-2.0
Project-URL: Homepage, https://github.com/rob-blackbourn/jetblack-serialization
Project-URL: Issues, https://github.com/rob-blackbourn/jetblack-serialization/issues
Keywords: serialization,JSON,XML,YAML
Classifier: Programming Language :: Python :: 3
Classifier: License :: OSI Approved :: MIT License
Classifier: Operating System :: OS Independent
Requires-Python: >=3.12
License-File: LICENSE
Requires-Dist: jetblack-iso8601==2.0.0
Provides-Extra: xml
Requires-Dist: lxml<6,>=5.2.2; extra == "xml"
Provides-Extra: yaml
Requires-Dist: pyyaml<7,>=6.0.1; extra == "yaml"
Provides-Extra: dev
Requires-Dist: pytest; extra == "dev"
Requires-Dist: coverage; extra == "dev"
Requires-Dist: autopep8; extra == "dev"
Requires-Dist: pylint; extra == "dev"
Requires-Dist: mypy; extra == "dev"
Requires-Dist: tox; extra == "dev"
Requires-Dist: virtualenv-pyenv; extra == "dev"
Requires-Dist: stringcase; extra == "dev"
Requires-Dist: types-pyyaml<7,>=6; extra == "dev"
Provides-Extra: docs
Requires-Dist: mkdocs; extra == "docs"
Requires-Dist: mkdocs-material; extra == "docs"
Requires-Dist: jetblack-markdown; extra == "docs"
Requires-Dist: mike; extra == "docs"
Dynamic: license-file
